py_spec/__init__.py
py_spec/ci/test.py
py_spec/input/__init__.py
py_spec/input/spec_namelist.py
py_spec/math/spec_fft.py
py_spec/math/spec_invfft.py
py_spec/output/__init__.py
py_spec/output/_plot_iota.py
py_spec/output/_plot_kam_surface.py
py_spec/output/_plot_modB.py
py_spec/output/_plot_poincare.py
py_spec/output/_plot_pressure.py
py_spec/output/_processing.py
py_spec/output/spec.py
py_spec-3.3.5.dist-info/METADATA
py_spec-3.3.5.dist-info/WHEEL
py_spec-3.3.5.dist-info/top_level.txt
py_spec-3.3.5.dist-info/RECORD
