Metadata-Version: 2.1
Name: py-spec
Version: 3.3.5
Summary: SPEC(Stepped-Pressure Equilibrium Code) python utilities
Author: SPEC developers
Author-email: Christopher Berg Smiet <christopher.smiet@epfl.ch>, Caoxiang Zhu <caoxiangzhu@gmail.com>
Maintainer-email: Christopher Berg Smiet <christopher.smiet@epfl.ch>
License: GNU 3.0
Classifier: Development Status :: 3 - Alpha
Classifier: License :: OSI Approved :: GNU Lesser General Public License v3 or later (LGPLv3+)
Classifier: Programming Language :: Python :: 3
Classifier: Topic :: Scientific/Engineering
Requires-Dist: f90nml
Requires-Dist: h5py
Requires-Dist: matplotlib
Requires-Dist: numpy >=1.21.1
Requires-Dist: scipy >=1.7.0
Requires-Dist: coilpy ; python_version < "3.12"
